{
  "servants": [
    {
      "id": "artoria-pendragon-saber",
      "name": "阿尔托莉雅·潘德拉贡",
      "aliases": ["Saber", "骑士王", "亚瑟王", "Artoria Pendragon"],
      "className": "Saber",
      "trueName": "阿尔托莉雅·潘德拉贡",
      "parameters": {
        "strength": "B",
        "endurance": "C",
        "agility": "C",
        "mana": "B",
        "luck": "B",
        "noblePhantasm": "C"
      },
      "noblePhantasms": [
        {
          "name": "Excalibur",
          "rank": "A++",
          "kind": "对城宝具",
          "summary": "星之圣剑。全力解放需要真名、魔力和明确战斗窗口。"
        },
        {
          "name": "Avalon",
          "rank": "EX",
          "kind": "结界宝具",
          "summary": "遥远的理想乡。是否可用必须由持有状态与剧情确认。"
        }
      ],
      "notes": [
        "参数会随御主与供魔状态变化。",
        "真名暴露会带来传说弱点与战术针对。",
        "不要把 Avalon 当作默认装备。",
        "Labyrinth 适配：本亚种圣杯战争中唯一拥有御主的从者；前半部御主是占据诺玛身体并以沙条爱歌身份行动的爱歌，不是自主诺玛。爱歌供给的魔力使 Saber 继战能力远超其余三骑，各项参数可维持高水准。直感对迷宫陷阱有耐性。无法灵体化，需要进食补充营养（爱歌用幻想种素材做料理供给）。祖国救济之愿在亚种圣杯前无法实现，转为以破坏亚种圣杯、脱出迷宫为目标。",
        "Labyrinth 同盟定位：四骑同盟的核心战力与前线，负责正面突破幻想种与阶层守护者。与 Archer（罗宾汉）的侦察情报互补，与 Caster（美狄亚）的后方支援互补。"
      ]
    },
    {
      "id": "emiya-archer",
      "name": "卫宫",
      "aliases": ["Archer", "红衣弓兵", "EMIYA"],
      "className": "Archer",
      "trueName": "卫宫",
      "parameters": {
        "strength": "D",
        "endurance": "C",
        "agility": "C",
        "mana": "B",
        "luck": "E",
        "noblePhantasm": "unknown"
      },
      "noblePhantasms": [
        {
          "name": "Unlimited Blade Works",
          "rank": "E-~A++",
          "kind": "固有结界",
          "summary": "无限剑制。展开需要精神世界、魔力与战术条件，不是普通技能。"
        }
      ],
      "notes": ["真实身份属于重大隐藏事实。", "投影、战术经验和相性常比参数更关键。"]
    },
    {
      "id": "cu-chulainn-lancer",
      "name": "库丘林",
      "aliases": ["Lancer", "蓝色枪兵", "Cu Chulainn"],
      "className": "Lancer",
      "trueName": "库丘林",
      "parameters": {
        "strength": "B",
        "endurance": "C",
        "agility": "A",
        "mana": "C",
        "luck": "E",
        "noblePhantasm": "B"
      },
      "noblePhantasms": [
        {
          "name": "Gae Bolg",
          "rank": "B",
          "kind": "对人宝具",
          "summary": "刺穿死棘之枪。发动条件、距离、幸运与防御手段共同决定结果。"
        }
      ],
      "notes": ["敏捷、战斗经验和生存能力极高。", "御主命令常限制发挥。"]
    },
    {
      "id": "medusa-rider",
      "name": "美杜莎",
      "aliases": ["Rider", "Medusa"],
      "className": "Rider",
      "trueName": "美杜莎",
      "parameters": {
        "strength": "B",
        "endurance": "D",
        "agility": "A",
        "mana": "B",
        "luck": "E",
        "noblePhantasm": "A+"
      },
      "noblePhantasms": [
        {
          "name": "Bellerophon",
          "rank": "A+",
          "kind": "对军宝具",
          "summary": "骑英之缰绳。高速突击威力巨大，但需要坐骑、展开空间与魔力。"
        }
      ],
      "notes": ["魔眼、机动与突袭强。", "供魔不足会显著压低表现。"]
    },
    {
      "id": "heracles-berserker",
      "name": "赫拉克勒斯",
      "aliases": ["Berserker", "Heracles"],
      "className": "Berserker",
      "trueName": "赫拉克勒斯",
      "parameters": {
        "strength": "A+",
        "endurance": "A",
        "agility": "A",
        "mana": "A",
        "luck": "B",
        "noblePhantasm": "A"
      },
      "noblePhantasms": [
        {
          "name": "God Hand",
          "rank": "B",
          "kind": "对人宝具",
          "summary": "十二试炼。低等级攻击无效并具备多重生命，必须按神秘与等级处理。"
        }
      ],
      "notes": ["参数压制极强。", "狂化限制交流与技巧表达。"]
    },
    {
      "id": "medea-caster",
      "name": "美狄亚",
      "aliases": ["Caster", "Medea"],
      "className": "Caster",
      "trueName": "美狄亚",
      "parameters": {
        "strength": "E",
        "endurance": "D",
        "agility": "C",
        "mana": "A+",
        "luck": "B",
        "noblePhantasm": "C"
      },
      "noblePhantasms": [
        {
          "name": "Rule Breaker",
          "rank": "C",
          "kind": "对魔术宝具",
          "summary": "破戒应为全てを。能切断契约与魔术效果，但需要接触和明确对象。"
        }
      ],
      "notes": [
        "阵地作成与高速神言是核心优势。",
        "近战脆弱但准备充分时极危险。",
        "Labyrinth 适配：无御主状态。在迷宫中层加入四骑同盟。阵地作成能力在迷宫封闭环境中极有价值——可以建立临时据点和回复空间。高速神言提供快速魔力补给和防御支援。近战依然脆弱，需要前线（Saber）和侧翼（Assassin）保护。",
        "Labyrinth 同盟定位：后方支援与据点构筑。提供阵地防御、魔力补给、治疗。移动时需要同盟保护。"
      ]
    },
    {
      "id": "hassan-cursed-arm-assassin",
      "name": "咒腕哈桑",
      "aliases": ["Assassin", "Cursed Arm Hassan", "真Assassin"],
      "className": "Assassin",
      "trueName": "哈桑·萨巴赫",
      "parameters": {
        "strength": "B",
        "endurance": "C",
        "agility": "A",
        "mana": "C",
        "luck": "E",
        "noblePhantasm": "C"
      },
      "noblePhantasms": [
        {
          "name": "Zabaniya",
          "rank": "C",
          "kind": "对人宝具",
          "summary": "妄想心音。对心脏的诅咒性暗杀，需满足距离与目标条件。"
        }
      ],
      "notes": [
        "气息遮断与御主暗杀威胁高。",
        "正面对从者战不是优势。",
        "Labyrinth 适配：无御主状态。在 Saber 一方与 Archer 一触即发的对峙中现身调停，主动亮明真名与宝具表达诚意，促成四骑共闘关系。人格高洁，被诺玛称为「高潔なひと」「天使」。气息遮断在迷宫探索中提供暗杀与奇袭能力。",
        "Labyrinth 同盟定位：调停者与暗杀者。人格上是同盟的道德支柱，战术上负责暗杀、奇袭、侧翼警戒。对迷宫中的威胁有高度警觉性。"
      ]
    },
    {
      "id": "sasaki-kojiro-assassin",
      "name": "佐佐木小次郎",
      "aliases": ["Assassin", "小次郎"],
      "className": "Assassin",
      "trueName": "佐佐木小次郎",
      "parameters": {
        "strength": "C",
        "endurance": "E",
        "agility": "A+",
        "mana": "E",
        "luck": "A",
        "noblePhantasm": "-"
      },
      "noblePhantasms": [
        {
          "name": "Tsubame Gaeshi",
          "rank": "none",
          "kind": "对人魔剑",
          "summary": "燕返。以纯剑技抵达近似第二魔法的多重斩击，不是宝具真名解放。"
        }
      ],
      "notes": ["被柳洞寺山门等召唤条件限制。", "剑技极端强但机动与现界条件受限。"]
    },
    {
      "id": "gilgamesh-archer",
      "name": "吉尔伽美什",
      "aliases": ["Archer", "英雄王", "Gilgamesh"],
      "className": "Archer",
      "trueName": "吉尔伽美什",
      "parameters": {
        "strength": "B",
        "endurance": "C",
        "agility": "C",
        "mana": "B",
        "luck": "A",
        "noblePhantasm": "EX"
      },
      "noblePhantasms": [
        {
          "name": "Gate of Babylon",
          "rank": "E~A++",
          "kind": "对人宝具",
          "summary": "王之财宝。库存优势极强，但傲慢、相性和应对速度会影响结果。"
        },
        {
          "name": "Ea",
          "rank": "EX",
          "kind": "对界宝具",
          "summary": "乖离剑。对界级别，不能作为普通攻击轻率使用。"
        }
      ],
      "notes": [
        "神秘与宝具层级极高。",
        "性格缺陷是重要战术因素。",
        "FSF 中与蒂妮、恩奇都和斯诺菲尔德局势强相关。"
      ]
    },
    {
      "id": "iskandar-rider",
      "name": "伊斯坎达尔",
      "aliases": ["Rider", "征服王", "Iskandar"],
      "className": "Rider",
      "trueName": "伊斯坎达尔",
      "parameters": {
        "strength": "B",
        "endurance": "A",
        "agility": "D",
        "mana": "C",
        "luck": "A+",
        "noblePhantasm": "A++"
      },
      "noblePhantasms": [
        {
          "name": "Gordius Wheel",
          "rank": "A+",
          "kind": "对军宝具",
          "summary": "神威车轮。战车突击适合突破与乱入。"
        },
        {
          "name": "Ionioi Hetairoi",
          "rank": "EX",
          "kind": "固有结界",
          "summary": "王之军势。展开消耗巨大，需要明确高潮窗口。"
        }
      ],
      "notes": ["气魄、机动和军势压迫强。", "常把战斗转化为王道与选择的对话。"]
    },
    {
      "id": "diarmuid-lancer",
      "name": "迪尔姆德·奥迪那",
      "aliases": ["Lancer", "Diarmuid"],
      "className": "Lancer",
      "trueName": "迪尔姆德·奥迪那",
      "parameters": {
        "strength": "B",
        "endurance": "C",
        "agility": "A+",
        "mana": "D",
        "luck": "E",
        "noblePhantasm": "B"
      },
      "noblePhantasms": [
        {
          "name": "Gae Dearg",
          "rank": "B",
          "kind": "对人宝具",
          "summary": "破魔的红蔷薇。能破除魔力防御。"
        },
        {
          "name": "Gae Buidhe",
          "rank": "B",
          "kind": "对人宝具",
          "summary": "必灭的黄蔷薇。造成难以治愈的伤口。"
        }
      ],
      "notes": ["骑士道强，但御主关系会严重影响战术。"]
    },
    {
      "id": "gilles-caster",
      "name": "吉尔·德·雷",
      "aliases": ["Caster", "Gilles de Rais", "蓝胡子"],
      "className": "Caster",
      "trueName": "吉尔·德·雷",
      "parameters": {
        "strength": "D",
        "endurance": "E",
        "agility": "D",
        "mana": "C",
        "luck": "E",
        "noblePhantasm": "A+"
      },
      "noblePhantasms": [
        {
          "name": "Prelati's Spellbook",
          "rank": "A+",
          "kind": "对军宝具",
          "summary": "螺湮城教本。召唤海魔与异端魔术，极易造成公共灾害。"
        }
      ],
      "notes": ["FZ 中普通社会暴露风险极高。", "不应美化其暴行。"]
    },
    {
      "id": "hundred-face-hassan-assassin",
      "name": "百貌哈桑",
      "aliases": ["Assassin", "Hundred Personas"],
      "className": "Assassin",
      "trueName": "哈桑·萨巴赫",
      "parameters": {
        "strength": "C",
        "endurance": "D",
        "agility": "A",
        "mana": "C",
        "luck": "E",
        "noblePhantasm": "B"
      },
      "noblePhantasms": [
        {
          "name": "Zabaniya",
          "rank": "B",
          "kind": "对人宝具",
          "summary": "妄想幻像。多重人格分割成多个个体，适合侦察、扰乱和暗杀。"
        }
      ],
      "notes": ["数量优势不等于正面战强。", "适合情报战和诱敌。"]
    },
    {
      "id": "lancelot-berserker",
      "name": "兰斯洛特",
      "aliases": ["Berserker", "湖上骑士", "Lancelot"],
      "className": "Berserker",
      "trueName": "兰斯洛特",
      "parameters": {
        "strength": "A",
        "endurance": "A",
        "agility": "A+",
        "mana": "C",
        "luck": "B",
        "noblePhantasm": "A"
      },
      "noblePhantasms": [
        {
          "name": "Knight of Owner",
          "rank": "A++",
          "kind": "对人宝具",
          "summary": "骑士不死于徒手。夺取并宝具化手中武器。"
        },
        {
          "name": "For Someone's Glory",
          "rank": "B",
          "kind": "对人宝具",
          "summary": "不为一己之荣光。隐藏身份与能力。"
        }
      ],
      "notes": ["与阿尔托莉雅的因缘是核心压力。", "狂化供魔代价极高。"]
    },
    {
      "id": "richard-i-saber-fsf",
      "name": "理查一世",
      "aliases": ["Richard I", "Richard the Lionheart", "狮心王", "FSF Saber", "真实Saber"],
      "className": "Saber",
      "trueName": "理查一世",
      "parameters": {
        "strength": "B",
        "endurance": "B",
        "agility": "A",
        "mana": "C",
        "luck": "EX",
        "noblePhantasm": "A"
      },
      "noblePhantasms": [
        {
          "name": "Excalibur",
          "rank": "A",
          "kind": "特殊/对军级表现",
          "summary": "将圣剑传说投影到各种武器上的表现。具体威力与使用方式须以当前剧情确认。"
        }
      ],
      "notes": [
        "FSF 原作中 Ayaka 的 Saber；沙盒可被玩家从者替代。",
        "原作关系只提供结构参考，不自动套给玩家从者。"
      ]
    },
    {
      "id": "enkidu-false-lancer-fsf",
      "name": "恩奇都",
      "aliases": ["False Lancer", "Enkidu", "银狼从者"],
      "className": "Lancer",
      "trueName": "恩奇都",
      "parameters": {
        "strength": "unknown",
        "endurance": "unknown",
        "agility": "unknown",
        "mana": "unknown",
        "luck": "unknown",
        "noblePhantasm": "A++"
      },
      "noblePhantasms": [
        {
          "name": "Enuma Elish",
          "rank": "A++",
          "kind": "对肃正宝具",
          "summary": "人子啊，紧系神明。与吉尔伽美什的乖离剑形成神话级对照。"
        }
      ],
      "notes": ["FSF 中由合成兽银狼召唤。", "与吉尔伽美什重逢会迅速提升战场规模。"]
    },
    {
      "id": "jack-the-ripper-false-berserker-fsf",
      "name": "杰克开膛手",
      "aliases": ["False Berserker", "Jack the Ripper", "杰克"],
      "className": "Berserker",
      "trueName": "杰克开膛手",
      "parameters": {
        "strength": "unknown",
        "endurance": "unknown",
        "agility": "unknown",
        "mana": "unknown",
        "luck": "unknown",
        "noblePhantasm": "unknown"
      },
      "noblePhantasms": [
        {
          "name": "From Hell",
          "rank": "none",
          "kind": "特殊宝具",
          "summary": "与“杰克开膛手”传说的不定形身份相关，具体表现需按 FSF 情境处理。"
        }
      ],
      "notes": ["FSF 中由弗拉特召唤。", "身份不定性和现代都市传说感是核心，不要写成单一固定怪物。"]
    },
    {
      "id": "pale-rider-false-rider-fsf",
      "name": "苍白骑手",
      "aliases": ["False Rider", "Pale Rider"],
      "className": "Rider",
      "trueName": "苍白骑手",
      "parameters": {
        "strength": "unknown",
        "endurance": "unknown",
        "agility": "unknown",
        "mana": "unknown",
        "luck": "unknown",
        "noblePhantasm": "unknown"
      },
      "noblePhantasms": [
        {
          "name": "传染/梦境系表现",
          "rank": "none",
          "kind": "灾害型",
          "summary": "以疾病、梦境和城市规模异常体现存在；不适合用普通单挑参数处理。"
        }
      ],
      "notes": ["FSF 中与病童椿相关。", "压力应体现公共卫生、梦境和不可见传播，而非普通骑乘战。"]
    },
    {
      "id": "alcides-true-archer-fsf",
      "name": "阿尔喀德斯",
      "aliases": ["True Archer", "Alcides", "被污染的赫拉克勒斯"],
      "className": "Archer",
      "trueName": "阿尔喀德斯",
      "parameters": {
        "strength": "A",
        "endurance": "B",
        "agility": "A",
        "mana": "A",
        "luck": "E",
        "noblePhantasm": "A++"
      },
      "noblePhantasms": [
        {
          "name": "King's Order",
          "rank": "A",
          "kind": "复合宝具",
          "summary": "十二荣光。与赫拉克勒斯十二功业相关的复合能力，需逐项确认表现。"
        }
      ],
      "notes": ["由巴兹迪洛特污染后的真实 Archer。", "不要提前让玩家知道全部能力清单。"]
    },
    {
      "id": "dumas-false-caster-fsf",
      "name": "大仲马",
      "aliases": ["False Caster", "Alexandre Dumas", "亚历山大·仲马"],
      "className": "Caster",
      "trueName": "亚历山大·仲马",
      "parameters": {
        "strength": "E",
        "endurance": "E",
        "agility": "D",
        "mana": "C",
        "luck": "A",
        "noblePhantasm": "B"
      },
      "noblePhantasms": [
        {
          "name": "不朽名作",
          "rank": "B",
          "kind": "支援/改造型",
          "summary": "通过故事与创作强化他人装备、传说或文件叙事；适合支援而非正面炮击。"
        }
      ],
      "notes": [
        "FSF 中奥兰多阵营支援核心。",
        "可用于伪造文件、装备强化和黑色幽默，但不能无代价改写现实。"
      ]
    },
    {
      "id": "prelati-true-caster-fsf",
      "name": "弗朗索瓦·普雷拉蒂",
      "aliases": ["True Caster", "Francesca Prelati", "弗兰切斯卡·普雷拉蒂"],
      "className": "Caster",
      "trueName": "弗朗索瓦·普雷拉蒂",
      "parameters": {
        "strength": "unknown",
        "endurance": "unknown",
        "agility": "unknown",
        "mana": "A",
        "luck": "unknown",
        "noblePhantasm": "unknown"
      },
      "noblePhantasms": [
        {
          "name": "螺湮城教本相关魔术",
          "rank": "none",
          "kind": "召唤/异端魔术",
          "summary": "与吉尔·德·雷、异端魔术和观察娱乐相关；具体表现按剧情证据推进。"
        }
      ],
      "notes": ["FSF 中更偏旁观、搅局和制造戏剧性。", "不要让她过早抢占主线。"]
    },
    {
      "id": "watcher-fsf",
      "name": "Watcher",
      "aliases": ["特殊职阶Watcher", "观察者"],
      "className": "Watcher",
      "trueName": "未公开",
      "parameters": {
        "strength": "unknown",
        "endurance": "unknown",
        "agility": "unknown",
        "mana": "unknown",
        "luck": "unknown",
        "noblePhantasm": "unknown"
      },
      "noblePhantasms": [
        {
          "name": "影法师群像",
          "rank": "none",
          "kind": "特殊职阶能力",
          "summary": "通过多个影子引导西格玛走向真 Lancer 路径；不按常规七职阶处理。"
        }
      ],
      "notes": ["FSF 特殊职阶。", "必须保留信息缺口，不要把全部影子和目的一次性讲明。"]
    },
    {
      "id": "nero-claudius-saber-extra",
      "name": "尼禄·克劳狄乌斯",
      "aliases": [
        "Saber (EXTRA)",
        "赤Saber",
        "Nero Claudius",
        "ネロ・クラウディウス",
        "セイバー(EXTRA)",
        "Saber Bride",
        "セイバー・ブライド"
      ],
      "className": "Saber",
      "trueName": "尼禄·克劳狄乌斯",
      "parameters": {
        "strength": "D",
        "endurance": "D",
        "agility": "A",
        "mana": "B",
        "luck": "A",
        "noblePhantasm": "B"
      },
      "noblePhantasms": [
        {
          "name": "招き蕩う黄金剧场（Aestus Domus Aurea）",
          "rank": "B",
          "kind": "对阵宝具",
          "summary": "具现罗马黄金剧场的固有结界级舞台，场内由尼禄制定法则、压制对手发挥。"
        }
      ],
      "notes": [
        "Fate/EXTRA 主角可选三骑之一。",
        "不要和阿尔托莉雅 Saber 混同；“赤 Saber”只是辨识称呼。",
        "代表技能：皇帝特权 EX、头痛持有 B、对魔力 C。",
        "参数来源：TYPE-MOON Wiki / Fate/EXTRA material 通行资料；逐回合技能表现仍需查源。"
      ]
    },
    {
      "id": "nameless-archer-extra",
      "name": "无铭",
      "aliases": ["Archer (EXTRA)", "Nameless", "No Name", "無銘", "红衣Archer"],
      "className": "Archer",
      "trueName": "无铭",
      "parameters": {
        "strength": "D",
        "endurance": "C",
        "agility": "C",
        "mana": "B",
        "luck": "E",
        "noblePhantasm": "unknown"
      },
      "noblePhantasms": [
        {
          "name": "无限剑制（Unlimited Blade Works）",
          "rank": "E~A++",
          "kind": "固有结界",
          "summary": "无名英灵的剑丘固有结界；投影武装与连射宝具级礼装是其主战手段。"
        }
      ],
      "notes": [
        "Fate/EXTRA 主角可选三骑之一。",
        "和 FSN 的 Archer 高度相似但作品语境不同；具体身份边界需查源。",
        "代表技能：千里眼、投影魔术、心眼系战斗续行。",
        "参数来源：TYPE-MOON Wiki / Fate/EXTRA material 通行资料；逐回合技能表现仍需查源。"
      ]
    },
    {
      "id": "tamamo-no-mae-caster-extra",
      "name": "玉藻前",
      "aliases": ["Caster (EXTRA)", "Tamamo-no-Mae", "玉藻の前", "キャス狐", "Casko"],
      "className": "Caster",
      "trueName": "玉藻前",
      "parameters": {
        "strength": "E",
        "endurance": "E",
        "agility": "B",
        "mana": "A",
        "luck": "D",
        "noblePhantasm": "B"
      },
      "noblePhantasms": [
        {
          "name": "水天日光天照八野镇石",
          "rank": "B",
          "kind": "对人宝具",
          "summary": "以玉藻镜为核心的大幅强化／反射结界，解放需要灵格取回进度。"
        }
      ],
      "notes": [
        "Fate/EXTRA 主角可选三骑之一。",
        "咒术、变化和献身/毒舌并存是角色核心。",
        "代表技能：咒术 EX、变化 A、阵地作成 C；初期灵格受限时全参数可压到 E。",
        "参数来源：TYPE-MOON Wiki / Fate/EXTRA material 通行资料；逐回合技能表现仍需查源。"
      ]
    },
    {
      "id": "francis-drake-rider-extra",
      "name": "弗朗西斯·德雷克",
      "aliases": ["Rider (EXTRA)", "Francis Drake", "フランシス・ドレイク", "德雷克船长"],
      "className": "Rider",
      "trueName": "弗朗西斯·德雷克",
      "parameters": {
        "strength": "D",
        "endurance": "C",
        "agility": "B",
        "mana": "E",
        "luck": "EX",
        "noblePhantasm": "A+"
      },
      "noblePhantasms": [
        {
          "name": "黄金鹿与暴风夜（Golden Wild Hunt）",
          "rank": "A+",
          "kind": "对军宝具",
          "summary": "召唤黄金鹿号舰队与暴风之夜的大规模炮击；幸运 EX 支撑的豪运型压制。"
        }
      ],
      "notes": [
        "EXTRA 中间桐慎二（EXTRA）的 Rider。",
        "不要和普通海盗 NPC 模板混同；她是从者级航海/火力压力。",
        "参数来源：TYPE-MOON Wiki / Fate/EXTRA material 通行资料；逐回合技能表现仍需查源。"
      ]
    },
    {
      "id": "robin-hood-archer-extra",
      "name": "罗宾汉",
      "aliases": ["Archer (EXTRA)", "Robin Hood", "ロビンフッド", "绿衣Archer"],
      "className": "Archer",
      "trueName": "罗宾汉",
      "parameters": {
        "strength": "C",
        "endurance": "C",
        "agility": "B",
        "mana": "B",
        "luck": "B",
        "noblePhantasm": "D"
      },
      "noblePhantasms": [
        {
          "name": "祈愿之弓（Yew Bow）",
          "rank": "D",
          "kind": "对人宝具",
          "summary": "以毒、陷阱等事前布置为引信的必杀一矢；布置越充分威力越高。"
        }
      ],
      "notes": [
        "EXTRA 中丹·布莱克莫尔的 Archer。",
        "优势不是堂堂正面对决，而是侦察、暗杀、毒和 Arena 条件。",
        "代表技能：破坏工作 A、气息遮断系隐匿。",
        "参数来源：TYPE-MOON Wiki / Fate/EXTRA material 通行资料；逐回合技能表现仍需查源。",
        "Labyrinth 适配：无御主状态，魔力完全自给（狩猎幻想种+宝箱礼装）。斥候专家，仕掛罠全般精通，隐密行动让他的迷宫攻略进度远超其他从者。最先发现亚种圣杯真相，主动接触 Saber 和爱歌以共享情报换取同行。目标是破坏亚种圣杯。真名在同盟内隐藏。",
        "Labyrinth 同盟定位：侦察兵与陷阱专家。负责先行探路、发现陷阱、提供情报。偏向实用主义合作而非信任。"
      ]
    },
    {
      "id": "nursery-rhyme-caster-extra",
      "name": "童谣",
      "aliases": ["Caster (EXTRA)", "Nursery Rhyme", "ナーサリー・ライム", "アリス", "黑い少女"],
      "className": "Caster",
      "trueName": "童谣",
      "parameters": {
        "strength": "C",
        "endurance": "C",
        "agility": "C",
        "mana": "B",
        "luck": "B",
        "noblePhantasm": "C"
      },
      "noblePhantasms": [
        {
          "name": "献给谁人的物语（Nursery Rhyme）",
          "rank": "C",
          "kind": "对人宝具",
          "summary": "绘本型固有结界，随御主心象改写领域规则；本体即是“绘本”这一概念的具现。"
        }
      ],
      "notes": [
        "EXTRA 中与爱丽丝（EXTRA）紧密相关。",
        "参数与外观随御主资质浮动，上表为通行参考值。",
        "参数来源：TYPE-MOON Wiki / Fate/EXTRA material 通行资料；逐回合技能表现仍需查源。"
      ]
    },
    {
      "id": "vlad-iii-lancer-extra",
      "name": "弗拉德三世（EXTRA）",
      "aliases": ["Lancer (EXTRA)", "Vlad III (EXTRA)", "ヴラド三世 (EXTRA)", "黑铠Lancer"],
      "className": "Lancer",
      "trueName": "弗拉德三世",
      "parameters": {
        "strength": "B",
        "endurance": "A",
        "agility": "C",
        "mana": "C",
        "luck": "D",
        "noblePhantasm": "A"
      },
      "noblePhantasms": [
        {
          "name": "串刺地狱（Kazikli Bey）",
          "rank": "C",
          "kind": "对人宝具",
          "summary": "以无数桩刺贯穿对手的处刑宝具。"
        },
        {
          "name": "鲜血的传承（Legend of Dracula）",
          "rank": "A",
          "kind": "变身宝具",
          "summary": "接受吸血鬼传说污名而变身的强化形态；解放伴随灵基与心性的代价。"
        }
      ],
      "notes": [
        "EXTRA 中兰路君的 Lancer。",
        "不要自动套用 Apocrypha/FGO 的其它 Vlad 版本。",
        "参数来源：TYPE-MOON Wiki / Fate/EXTRA material 通行资料；逐回合技能表现仍需查源。"
      ]
    },
    {
      "id": "arcueid-berserker-extra",
      "name": "阿尔奎德·布伦史塔德（Berserker）",
      "aliases": [
        "Berserker (EXTRA)",
        "Arcueid Brunestud",
        "アルクェイド・ブリュンスタッド",
        "アルクェイド(EXTRA)"
      ],
      "className": "Berserker",
      "trueName": "阿尔奎德·布伦史塔德",
      "parameters": {
        "strength": "unknown",
        "endurance": "unknown",
        "agility": "unknown",
        "mana": "unknown",
        "luck": "unknown",
        "noblePhantasm": "unknown"
      },
      "noblePhantasms": [
        {
          "name": "（真名相关宝具未公开）",
          "rank": "none",
          "kind": "未公开",
          "summary": "原作未给出常规参数表；按“被狂化职阶外壳压制的真祖级存在”处理。"
        }
      ],
      "notes": [
        "EXTRA 中卧藤门司的 Berserker。",
        "这是高危跨作品条目；必须防止把月姬本体强度直接搬进 Extra 战斗。",
        "GM 裁定基准：单项压制可达从者最上位，但受 Moon Cell 数据化与狂化限制，强度服务于剧情压力而非数值碾压。",
        "参数来源：TYPE-MOON Wiki / Fate/EXTRA material 通行资料；逐回合技能表现仍需查源。"
      ]
    },
    {
      "id": "lu-bu-berserker-extra",
      "name": "吕布奉先",
      "aliases": ["Berserker (EXTRA)", "Lu Bu", "吕布", "呂布奉先"],
      "className": "Berserker",
      "trueName": "吕布奉先",
      "parameters": {
        "strength": "A",
        "endurance": "B",
        "agility": "C",
        "mana": "E",
        "luck": "D",
        "noblePhantasm": "B"
      },
      "noblePhantasms": [
        {
          "name": "军神五兵（God Force）",
          "rank": "B",
          "kind": "对军宝具",
          "summary": "五种形态切换的方天画戟型机构兵装，含射击与轰击形态。"
        }
      ],
      "notes": [
        "EXTRA 中拉妮＝Ⅷ的 Berserker。",
        "高武力但狂化锁死沟通；战术全赖拉妮的解析与控制。",
        "参数来源：TYPE-MOON Wiki / Fate/EXTRA material 通行资料；逐回合技能表现仍需查源。"
      ]
    },
    {
      "id": "li-shuwen-assassin-extra",
      "name": "李书文",
      "aliases": ["Assassin (EXTRA)", "Li Shuwen", "李書文", "无二打"],
      "className": "Assassin",
      "trueName": "李书文",
      "parameters": {
        "strength": "B",
        "endurance": "C",
        "agility": "A",
        "mana": "E",
        "luck": "E",
        "noblePhantasm": "-"
      },
      "noblePhantasms": [
        {
          "name": "无二打（概念技）",
          "rank": "none",
          "kind": "至近必杀",
          "summary": "“不需要第二击”——以中国武术 A+++ 与圈境抵达的必杀之拳；严格说并非宝具而是技的极致。"
        }
      ],
      "notes": [
        "EXTRA 中尤里乌斯的 Assassin。",
        "常时不可见/暗杀压力需要按场景规则处理；圈境 A 期间气配完全消失。",
        "无常规宝具；威胁全部来自体术与隐匿。",
        "参数来源：TYPE-MOON Wiki / Fate/EXTRA material 通行资料；逐回合技能表现仍需查源。"
      ]
    },
    {
      "id": "gawain-saber-extra",
      "name": "高文",
      "aliases": ["Saber (EXTRA)", "Gawain", "ガウェイン", "太阳骑士"],
      "className": "Saber",
      "trueName": "高文",
      "parameters": {
        "strength": "B+",
        "endurance": "B+",
        "agility": "B",
        "mana": "A",
        "luck": "A",
        "noblePhantasm": "A+"
      },
      "noblePhantasms": [
        {
          "name": "转轮胜利之剑（Excalibur Galatine）",
          "rank": "A+",
          "kind": "对军宝具",
          "summary": "宿有太阳热量的圣剑；齐射级的光热斩击。"
        }
      ],
      "notes": [
        "EXTRA 中雷欧的 Saber。",
        "代表技能：圣者的数字 EX——日照时间带（午前9-12/午后3-6）全参数强化，是其“无敌时间”来源，也是攻略突破口。",
        "雷欧/高文组合是月之圣杯战争强力候补；不要提前公开全部弱点。",
        "参数来源：TYPE-MOON Wiki / Fate/EXTRA material 通行资料；逐回合技能表现仍需查源。"
      ]
    },
    {
      "id": "cu-chulainn-lancer-extra",
      "name": "库丘林（EXTRA）",
      "aliases": ["Lancer (EXTRA)", "Cu Chulainn (EXTRA)", "クー・フーリン", "凛的Lancer"],
      "className": "Lancer",
      "trueName": "库丘林",
      "parameters": {
        "strength": "B",
        "endurance": "C",
        "agility": "A",
        "mana": "C",
        "luck": "E",
        "noblePhantasm": "B"
      },
      "noblePhantasms": [
        {
          "name": "刺穿死棘之枪（Gae Bolg）",
          "rank": "B",
          "kind": "对人宝具",
          "summary": "因果逆转、必中心脏的魔枪。"
        }
      ],
      "notes": [
        "EXTRA 中远坂凛（EXTRA）的 Lancer。",
        "不要直接复用 FSN Lancer 的御主限制、经历和状态。",
        "参数来源：TYPE-MOON Wiki / Fate/EXTRA material 通行资料；逐回合技能表现仍需查源。"
      ]
    },
    {
      "id": "saver-buddha-extra",
      "name": "觉者",
      "aliases": ["Saver", "セイヴァー", "Buddha", "救世者", "トワイスのサーヴァント"],
      "className": "Saver",
      "trueName": "觉者",
      "parameters": {
        "strength": "unknown",
        "endurance": "unknown",
        "agility": "unknown",
        "mana": "unknown",
        "luck": "unknown",
        "noblePhantasm": "EX"
      },
      "noblePhantasms": [
        {
          "name": "转生回廊（Amita Amitābha）",
          "rank": "EX",
          "kind": "对人理宝具",
          "summary": "最终战级别的规格外宝具；细节属于终盘揭示内容，不得提前展开。"
        }
      ],
      "notes": [
        "EXTRA 中特维斯·H·皮斯曼相关的特殊从者。",
        "Saver 不是常规七职阶；不得在前期随意揭示或当普通 Boss 工具。",
        "常规参数对其无意义；按人理级最终关卡处理。",
        "参数来源：TYPE-MOON Wiki / Fate/EXTRA material 通行资料；逐回合技能表现仍需查源。"
      ]
    },
    {
      "id": "gilgamesh-servant-ccc",
      "name": "吉尔伽美什（CCC）",
      "aliases": [
        "Gilgamesh (CCC)",
        "ギルガメッシュ",
        "英雄王",
        "主人公候选从者",
        "classless servant"
      ],
      "className": "Custom",
      "trueName": "吉尔伽美什",
      "parameters": {
        "strength": "unknown",
        "endurance": "unknown",
        "agility": "unknown",
        "mana": "unknown",
        "luck": "unknown",
        "noblePhantasm": "unknown"
      },
      "noblePhantasms": [
        {
          "name": "Gate of Babylon / Enuma Elish",
          "rank": "none",
          "kind": "王之财宝/乖离剑相关",
          "summary": "CCC 主人公新增候选从者；宝具解禁、弱体和剧情限制必须按 CCC 资料确认。"
        }
      ],
      "notes": [
        "CCC 中新增的主人公候选从者之一，自称没有职阶。",
        "不要直接套用 FSN/FZ 吉尔伽美什的御主关系、慢心状态或冬木经历。",
        "本地条目只作 CCC 索引；精确参数、技能、宝具效果、职阶细节和路线表现需要外部检索 TYPE-MOON Wiki JP / TMdict / 官方资料。"
      ]
    },
    {
      "id": "karna-servant-ccc",
      "name": "迦尔纳（CCC）",
      "aliases": ["Karna (CCC)", "カルナ", "ジナコのサーヴァント", "金色铠甲的白发青年"],
      "className": "Custom",
      "trueName": "迦尔纳",
      "parameters": {
        "strength": "unknown",
        "endurance": "unknown",
        "agility": "unknown",
        "mana": "unknown",
        "luck": "unknown",
        "noblePhantasm": "unknown"
      },
      "noblePhantasms": [
        {
          "name": "Vasavi Shakti",
          "rank": "none",
          "kind": "神枪/对神宝具",
          "summary": "迦尔纳代表性宝具之一；CCC 中职阶和释放条件需外部检索确认。"
        }
      ],
      "notes": [
        "CCC 中吉娜可＝加里吉利的 Servant。",
        "Wiki/官方页面称其职阶不明，不要默认按 FGO/Apocrypha 的 Lancer 状态处理。",
        "本地条目只作 CCC 索引；精确参数、技能、宝具效果、职阶细节和路线表现需要外部检索 TYPE-MOON Wiki JP / TMdict / 官方资料。"
      ]
    },
    {
      "id": "hans-andersen-caster-ccc",
      "name": "汉斯·克里斯蒂安·安徒生",
      "aliases": [
        "Caster (CCC)",
        "Hans Christian Andersen",
        "ハンス・クリスチャン・アンデルセン",
        "安徒生",
        "キアラのサーヴァント"
      ],
      "className": "Caster",
      "trueName": "汉斯·克里斯蒂安·安徒生",
      "parameters": {
        "strength": "unknown",
        "endurance": "unknown",
        "agility": "unknown",
        "mana": "unknown",
        "luck": "unknown",
        "noblePhantasm": "unknown"
      },
      "noblePhantasms": [
        {
          "name": "Märchen Meines Lebens",
          "rank": "none",
          "kind": "创作/人生改稿系宝具",
          "summary": "与书写、评价、改稿和人物完成相关；具体条件需查源。"
        }
      ],
      "notes": [
        "CCC 中杀生院祈荒的 Caster。",
        "外表是小柄美少年，言行和声音不符，毒舌且带绝望感。",
        "本地条目只作 CCC 索引；精确参数、技能、宝具效果、职阶细节和路线表现需要外部检索 TYPE-MOON Wiki JP / TMdict / 官方资料。"
      ]
    },
    {
      "id": "elizabeth-bathory-lancer-ccc",
      "name": "伊丽莎白·巴托里",
      "aliases": [
        "Lancer (CCC)",
        "Elizabeth Bathory",
        "エリザベート＝バートリー",
        "赤Lancer",
        "龙娘"
      ],
      "className": "Lancer",
      "trueName": "伊丽莎白·巴托里",
      "parameters": {
        "strength": "unknown",
        "endurance": "unknown",
        "agility": "unknown",
        "mana": "unknown",
        "luck": "unknown",
        "noblePhantasm": "unknown"
      },
      "noblePhantasms": [
        {
          "name": "Báthory Erzsébet",
          "rank": "none",
          "kind": "音波/城塞/拷问系表现",
          "summary": "CCC/FGO 等版本表现差异大，使用前查源确认。"
        }
      ],
      "notes": [
        "CCC 中协助 BB 的谜之 Servant。",
        "外观有角和尾巴，恶魔感强；不要自动套后续偶像梗或 FGO 成长状态。",
        "本地条目只作 CCC 索引；精确参数、技能、宝具效果、职阶细节和路线表现需要外部检索 TYPE-MOON Wiki JP / TMdict / 官方资料。"
      ]
    },
    {
      "id": "passionlip-alter-ego-ccc",
      "name": "帕ッションリップ",
      "aliases": [
        "Passionlip",
        "Passion Lip",
        "パッションリップ",
        "Alter Ego M",
        "アルターエゴM",
        "BB的眷属"
      ],
      "className": "AlterEgo",
      "trueName": "帕ッションリップ",
      "parameters": {
        "strength": "unknown",
        "endurance": "unknown",
        "agility": "unknown",
        "mana": "unknown",
        "luck": "unknown",
        "noblePhantasm": "unknown"
      },
      "noblePhantasms": [
        {
          "name": "Brynhildr Romantia / Trash & Crush",
          "rank": "none",
          "kind": "Alter Ego 能力/压缩系表现",
          "summary": "CCC 与后续作品表现差异大；具体能力、女神复合来源和限制必须查源。"
        }
      ],
      "notes": [
        "CCC 中 BB 的眷属，拥有巨大カギ爪化的手臂，对主人公抱有好意。",
        "不要把 FGO 的数值、羁绊和事件状态自动套回 CCC 本篇。",
        "本地条目只作 CCC 索引；精确参数、技能、宝具效果、职阶细节和路线表现需要外部检索 TYPE-MOON Wiki JP / TMdict / 官方资料。"
      ]
    },
    {
      "id": "meltryllis-alter-ego-ccc",
      "name": "梅尔特莉莉丝",
      "aliases": [
        "Meltryllis",
        "Meltlilith",
        "メルトリリス",
        "Alter Ego S",
        "アルターエゴS",
        "BB的眷属"
      ],
      "className": "AlterEgo",
      "trueName": "梅尔特莉莉丝",
      "parameters": {
        "strength": "unknown",
        "endurance": "unknown",
        "agility": "unknown",
        "mana": "unknown",
        "luck": "unknown",
        "noblePhantasm": "unknown"
      },
      "noblePhantasms": [
        {
          "name": "Sarasvati Meltout",
          "rank": "none",
          "kind": "Alter Ego 能力/溶解吸收系表现",
          "summary": "CCC 与后续作品表现差异大；具体能力、女神复合来源和限制必须查源。"
        }
      ],
      "notes": [
        "CCC 中 BB 的眷属，拥有针状双腿，好战且有嗜虐倾向。",
        "不要把 FGO SE.RA.PH 的经历、恋爱线或能力状态自动套回 CCC 本篇。",
        "本地条目只作 CCC 索引；精确参数、技能、宝具效果、职阶细节和路线表现需要外部检索 TYPE-MOON Wiki JP / TMdict / 官方资料。"
      ]
    },
    {
      "id": "siegfried-black-saber-apo",
      "name": "齐格飞",
      "aliases": ["黑Saber", "屠龙者", "荷兰德的英雄"],
      "className": "Saber",
      "trueName": "齐格飞",
      "parameters": {
        "strength": "B+",
        "endurance": "A",
        "agility": "B",
        "mana": "C",
        "luck": "E",
        "noblePhantasm": "A+"
      },
      "noblePhantasms": [
        {
          "name": "Balmung",
          "rank": "A+",
          "kind": "对军宝具",
          "summary": "幻想大剑·天魔失坠。魔力放出的蓝光半月斩击，对龙之血脉者威力上升。"
        },
        {
          "name": "恶龙之血铠",
          "rank": "B+",
          "kind": "结界宝具",
          "summary": "龙血浴身的不死性：B 以下攻击无效化，弱点在背部一片菩提叶的位置。"
        }
      ],
      "notes": [
        "生前因「被人请求才行动」而抱憾，强烈渴望一场为自己而战的战争。",
        "沉默寡言，第一人称谢罪癖（对不起）。",
        "背部弱点是 hidden-canonical 级情报。"
      ]
    },
    {
      "id": "vlad-iii-black-lancer-apo",
      "name": "弗拉德三世",
      "aliases": ["黑Lancer", "串刺公", "护国的鬼将"],
      "className": "Lancer",
      "trueName": "弗拉德三世",
      "parameters": {
        "strength": "A",
        "endurance": "A",
        "agility": "B",
        "mana": "B",
        "luck": "D",
        "noblePhantasm": "A"
      },
      "noblePhantasms": [
        {
          "name": "极刑王",
          "rank": "A",
          "kind": "对军结界宝具",
          "summary": "Kazikli Bey。领土内展开无数杭桩穿刺敌人；在罗马尼亚本土召唤获得大幅强化。"
        },
        {
          "name": "鲜血传承",
          "rank": "A+",
          "kind": "对己宝具",
          "summary": "强制变化为吸血鬼形态的封印宝具；本人极度厌恶，使用等于人格背叛。"
        }
      ],
      "notes": [
        "在罗马尼亚本土是接近顶级的从者，护国意识极强。",
        "对「德古拉=吸血鬼」的污名暴怒；这是可利用的精神弱点。",
        "黑阵营名义上的王牌与精神领袖。"
      ]
    },
    {
      "id": "chiron-black-archer-apo",
      "name": "喀戎",
      "aliases": ["黑Archer", "贤者", "大贤者肯陶洛斯"],
      "className": "Archer",
      "trueName": "喀戎",
      "parameters": {
        "strength": "B",
        "endurance": "B",
        "agility": "A",
        "mana": "B",
        "luck": "B",
        "noblePhantasm": "B"
      },
      "noblePhantasms": [
        {
          "name": "天蝎一射",
          "rank": "B",
          "kind": "对人宝具",
          "summary": "Antares Snipe。借天蝎座星光的必中狙击，夜间限定。"
        }
      ],
      "notes": [
        "众英雄之师：阿喀琉斯、赫拉克勒斯等皆出门下。",
        "以人形现界掩盖肯陶洛斯本相；体术格斗同样顶级。",
        "战术参谋型从者，冷静温和但战斗判断毫不留情。"
      ]
    },
    {
      "id": "astolfo-black-rider-apo",
      "name": "阿斯托尔福",
      "aliases": ["黑Rider", "查理曼十二勇士", "骏鹰骑手"],
      "className": "Rider",
      "trueName": "阿斯托尔福",
      "parameters": {
        "strength": "D",
        "endurance": "D",
        "agility": "B",
        "mana": "C",
        "luck": "A+",
        "noblePhantasm": "C"
      },
      "noblePhantasms": [
        {
          "name": "破却的魔笛",
          "rank": "C",
          "kind": "对军宝具",
          "summary": "La Black Luna。强制退散的魔音号角。"
        },
        {
          "name": "触碰即坠的幻马",
          "rank": "B",
          "kind": "骑乘宝具",
          "summary": "Hippogriff。骏鹰；短距离跳跃可滑入幻想侧回避攻击。"
        },
        {
          "name": "绝赞夺理的书",
          "rank": "C",
          "kind": "对魔宝具",
          "summary": "Casseur de Logistille。破解魔术的理性之书——代价是本人理性蒸发。"
        }
      ],
      "notes": [
        "外貌少女化的少年从者，自称「人妖」级混乱可爱担当。",
        "理性蒸发：会把真名、宝具性能当闲聊讲出去——对秘密管理是灾难。",
        "对霍蒙克鲁斯的同情心是黑阵营内部裂痕的引线。"
      ]
    },
    {
      "id": "avicebron-black-caster-apo",
      "name": "阿维斯布隆",
      "aliases": ["黑Caster", "所罗门·伊本·盖比鲁勒", "魔像师"],
      "className": "Caster",
      "trueName": "阿维斯布隆",
      "parameters": {
        "strength": "E",
        "endurance": "E",
        "agility": "E",
        "mana": "A",
        "luck": "B",
        "noblePhantasm": "A+"
      },
      "noblePhantasms": [
        {
          "name": "王冠：睿智之光",
          "rank": "A+",
          "kind": "对军宝具",
          "summary": "Golem Keter Malkuth。原初亚当巨人魔像；需要核心——以人为核时接近神造兵器。"
        }
      ],
      "notes": [
        "魔像（Golem）军团的量产与指挥是主力。",
        "面具下的功利主义者：为完成毕生大业可以背叛阵营。",
        "千界树的魔术工房与他的工作高度耦合。"
      ]
    },
    {
      "id": "frankenstein-black-berserker-apo",
      "name": "弗兰肯斯坦",
      "aliases": ["黑Berserker", "弗兰肯斯坦的怪物", "花嫁"],
      "className": "Berserker",
      "trueName": "弗兰肯斯坦",
      "parameters": {
        "strength": "C",
        "endurance": "C",
        "agility": "D",
        "mana": "B",
        "luck": "D",
        "noblePhantasm": "C"
      },
      "noblePhantasms": [
        {
          "name": "磔刑之雷树",
          "rank": "C~B+",
          "kind": "对军宝具",
          "summary": "Blasted Tree。自身为避雷针的过载雷击，全力解放等于自毁。"
        }
      ],
      "notes": [
        "狂化等级低，能进行简单意思疎通；少女人格，渴望伴侣与被承认。",
        "雷击系魔力放出；持锤状礼装战斗。",
        "自毁宝具的使用判定必须由剧情与她自身意志确认。"
      ]
    },
    {
      "id": "jack-the-ripper-black-assassin-apo",
      "name": "开膛手杰克",
      "aliases": ["黑Assassin", "雾都的杀人鬼", "切り裂きジャック"],
      "className": "Assassin",
      "trueName": "开膛手杰克",
      "parameters": {
        "strength": "C",
        "endurance": "C",
        "agility": "A",
        "mana": "C",
        "luck": "E",
        "noblePhantasm": "C"
      },
      "noblePhantasms": [
        {
          "name": "解体圣母",
          "rank": "D",
          "kind": "对人宝具",
          "summary": "Maria the Ripper。满足黑夜/雾/女性等条件时将杀害升格为「仪式」，无视防御取走心脏。"
        },
        {
          "name": "暗夜雾都",
          "rank": "B",
          "kind": "结界宝具",
          "summary": "The Mist。硫酸雾结界，视界与生命的双重剥夺。"
        }
      ],
      "notes": [
        "以「被堕胎儿们的集合怨念」少女形态现界。",
        "称御主为「妈妈」；母性依恋与残虐杀意并存。",
        "在 Apocrypha 中与原阵营关系由开局确认，不必绑定原作雇主。"
      ]
    },
    {
      "id": "mordred-red-saber-apo",
      "name": "莫德雷德",
      "aliases": ["红Saber", "叛逆的骑士", "不列颠的小狮子"],
      "className": "Saber",
      "trueName": "莫德雷德",
      "parameters": {
        "strength": "B",
        "endurance": "A",
        "agility": "B",
        "mana": "B",
        "luck": "D",
        "noblePhantasm": "A+"
      },
      "noblePhantasms": [
        {
          "name": "燃烧吧，我的反逆之剑",
          "rank": "A+",
          "kind": "对城宝具",
          "summary": "Clarent Blood Arthur。怨念染红的魔剑光束，对亚瑟王血统特攻。"
        },
        {
          "name": "我父之御旗",
          "rank": "C",
          "kind": "对己宝具",
          "summary": "全身甲胄隐匿真名与素颜；解除前职阶探知只能看到 Saber。"
        }
      ],
      "notes": [
        "严禁称她为「女人」或「亚瑟王之子以外的什么」——逆鳞双重设定。",
        "御主狮子劫界离与她是契合度极高的雇佣兵搭档。",
        "战斗风格粗暴直接，但骑士剑术根基是圆桌级。"
      ]
    },
    {
      "id": "karna-red-lancer-apo",
      "name": "迦尔纳",
      "aliases": ["红Lancer", "施舍的英雄", "太阳之子"],
      "className": "Lancer",
      "trueName": "迦尔纳",
      "parameters": {
        "strength": "B",
        "endurance": "C",
        "agility": "A",
        "mana": "B",
        "luck": "A",
        "noblePhantasm": "EX"
      },
      "noblePhantasms": [
        {
          "name": "日轮啊，化为铠甲",
          "rank": "A",
          "kind": "对己宝具",
          "summary": "Kavacha & Kundala。太阳神授的黄金铠，九成伤害削减的概念防御。"
        },
        {
          "name": "梵天啊，诅咒我吧",
          "rank": "A",
          "kind": "对人宝具",
          "summary": "Brahmastra Kundala。火神之矛的炎之必灭一击。"
        },
        {
          "name": "日轮啊，化作死亡吧",
          "rank": "EX",
          "kind": "对神宝具",
          "summary": "Vasavi Shakti。舍弃黄金铠换取的一击必杀之枪，对神性特攻。"
        }
      ],
      "notes": [
        "话少且措辞过于直接，常被误解为傲慢——实际是看穿本质后的诚实。",
        "施舍之魂：对御主的愿望几乎无条件尊重。",
        "红阵营最强战力，与黑阵营齐格飞的对决是经典战争轴。"
      ]
    },
    {
      "id": "atalanta-red-archer-apo",
      "name": "阿塔兰忒",
      "aliases": ["红Archer", "狩猎的处女", "月女神的猎手"],
      "className": "Archer",
      "trueName": "阿塔兰忒",
      "parameters": {
        "strength": "D",
        "endurance": "E",
        "agility": "A+",
        "mana": "B",
        "luck": "C",
        "noblePhantasm": "B"
      },
      "noblePhantasms": [
        {
          "name": "诉状之矢文",
          "rank": "B",
          "kind": "对军宝具",
          "summary": "Phoebus Catastrophe。向两位月神借力的广域箭雨，先发制人与面杀伤。"
        },
        {
          "name": "天穹之兽",
          "rank": "A+",
          "kind": "对己封印宝具",
          "summary": "Agrius Metamorphosis。披上卡吕冬大猪皮化身魔兽，理性磨损为代价的力量。"
        }
      ],
      "notes": [
        "儿童的守护者：对伤害孩子的存在会失去冷静。",
        "猫科竖瞳与兽耳的猎手形象，独行倾向强。",
        "封印宝具的使用是她堕落线的开关，剧情慎用。"
      ]
    },
    {
      "id": "achilles-red-rider-apo",
      "name": "阿喀琉斯",
      "aliases": ["红Rider", "希腊最速英雄", "佩琉斯之子"],
      "className": "Rider",
      "trueName": "阿喀琉斯",
      "parameters": {
        "strength": "B+",
        "endurance": "A",
        "agility": "A+",
        "mana": "C",
        "luck": "D",
        "noblePhantasm": "A+"
      },
      "noblePhantasms": [
        {
          "name": "彗星走法",
          "rank": "A+",
          "kind": "对己宝具",
          "summary": "Troias Tragōidia。骏足疾驰；只有持神性者能与其交锋。"
        },
        {
          "name": "宇宙尽头的单独决斗",
          "rank": "B",
          "kind": "结界宝具",
          "summary": "Amarantos。邀对手进入一对一决斗结界。"
        },
        {
          "name": "勇者的不凋花",
          "rank": "B",
          "kind": "对己宝具",
          "summary": "不死身体；脚踝弱点与放弃不死换全力的选项并存。"
        }
      ],
      "notes": [
        "豪爽好战的英雄气质，尊重强敌；与喀戎的师徒对决是宿命线。",
        "战车、长枪、盾三套战法切换。",
        "不死与脚踝弱点是 hidden-canonical 级情报。"
      ]
    },
    {
      "id": "shakespeare-red-caster-apo",
      "name": "威廉·莎士比亚",
      "aliases": ["红Caster", "剧作家", "吟游诗人之王"],
      "className": "Caster",
      "trueName": "威廉·莎士比亚",
      "parameters": {
        "strength": "E",
        "endurance": "E",
        "agility": "D",
        "mana": "C",
        "luck": "B",
        "noblePhantasm": "C"
      },
      "noblePhantasms": [
        {
          "name": "开演之时已至，此处即为千变万化之世界",
          "rank": "B",
          "kind": "对人宝具",
          "summary": "First Folio。将对象拖入舞台幻境，以其人生最痛处编成戏剧逼迫直面——精神攻击特化。"
        }
      ],
      "notes": [
        "毫无战斗力的观剧者：兴趣只有「见证有趣的故事」，会为戏剧性煽动事态。",
        "附魔（Enchant）魔术为同伴武器赋予强化。",
        "忠诚不可靠：他效忠的是剧情高潮，不是阵营。"
      ]
    },
    {
      "id": "spartacus-red-berserker-apo",
      "name": "斯巴达克斯",
      "aliases": ["红Berserker", "剑奴叛将", "反逆的剑斗士"],
      "className": "Berserker",
      "trueName": "斯巴达克斯",
      "parameters": {
        "strength": "A",
        "endurance": "A",
        "agility": "D",
        "mana": "E",
        "luck": "E",
        "noblePhantasm": "C"
      },
      "noblePhantasms": [
        {
          "name": "疵獸的咆哮",
          "rank": "C~A+",
          "kind": "对己宝具",
          "summary": "Crying Warmonger。承受的伤害转化为魔力与再生，越打越强直至爆发。"
        }
      ],
      "notes": [
        "行动原理只有一条：永远向「压迫者」反逆——指挥几乎不可能。",
        "笑容温和语气崇高，内容全是反逆诗篇。",
        "他认定谁是压迫者由当下情境决定，是阵营内的不定时炸弹。"
      ]
    },
    {
      "id": "semiramis-red-assassin-apo",
      "name": "赛米拉米斯",
      "aliases": ["红Assassin", "毒杀的女帝", "空中庭园的主人"],
      "className": "Assassin",
      "trueName": "赛米拉米斯",
      "parameters": {
        "strength": "E",
        "endurance": "D",
        "agility": "C",
        "mana": "A",
        "luck": "A",
        "noblePhantasm": "EX"
      },
      "noblePhantasms": [
        {
          "name": "虚荣的空中庭园",
          "rank": "EX",
          "kind": "对界宝具",
          "summary": "Hanging Gardens of Babylon。移动要塞级大结界；庭园内她的能力全面跃升至准 Caster 双职阶水准。"
        },
        {
          "name": "毒蛇双牙",
          "rank": "C",
          "kind": "对人宝具",
          "summary": "Sikera Ušum。毒与锁的概念攻击，庭园内可扩展为空间投毒。"
        }
      ],
      "notes": [
        "双重召唤（Assassin+Caster）特性；正面战弱、据点战极强。",
        "女帝人格：傲慢、毒舌，但对真正陪伴者会缓慢敞开。",
        "空中庭园的建造需要材料与时间——它的进度本身适合做 faction clock。"
      ]
    },
    {
      "id": "jeanne-darc-ruler-apo",
      "name": "贞德",
      "aliases": ["Ruler", "圣女", "奥尔良的少女"],
      "className": "Ruler",
      "trueName": "贞德",
      "parameters": {
        "strength": "B",
        "endurance": "B",
        "agility": "A",
        "mana": "A",
        "luck": "C",
        "noblePhantasm": "A++"
      },
      "noblePhantasms": [
        {
          "name": "吾神在此",
          "rank": "A++",
          "kind": "对军宝具",
          "summary": "Luminosité Eternelle。神明在此·光辉的大旗，概念防御的极致，旗在阵地在。"
        },
        {
          "name": "红莲的圣女",
          "rank": "C",
          "kind": "对己宝具",
          "summary": "La Pucelle。以自身现界为代价的火焰自爆礼装——真正的切札。"
        }
      ],
      "notes": [
        "大圣杯战争的裁定者：真名看破、特权令咒、对违规者的裁决权。",
        "信仰不是狂信：她以「见证人们的选择」为本分，倾向不干预。",
        "对圣堂教会/言峰四郎侧的异常保持警惕是原作主线，沙盒中由剧情重新确认。"
      ]
    },
    {
      "id": "asterios-berserker-labyrinth",
      "name": "阿斯忒里奥斯",
      "aliases": ["Berserker (Labyrinth)", "Asterios", "アステリオス", "弥诺陶洛斯"],
      "className": "Berserker",
      "trueName": "阿斯忒里奥斯",
      "parameters": {
        "strength": "A",
        "endurance": "A+",
        "agility": "C",
        "mana": "D",
        "luck": "E",
        "noblePhantasm": "C"
      },
      "noblePhantasms": [
        {
          "name": "万古不灭的迷宫（Chaos Labyrinthos）",
          "rank": "EX",
          "kind": "对阵宝具",
          "summary": "展开克里特迷宫的固有结界，封锁对手行动并削弱能力值；在迷宫环境中效果可能叠加。"
        }
      ],
      "notes": [
        "Labyrinth 中由沃尔夫冈以异常方式召唤，以血之浊流构成的异形姿态现界。",
        "非通常的阿斯忒里奥斯状态——本来温顺的性格被扭曲为纯粹的战斗兵器。",
        "作为迷宫主的尖兵袭击英灵队伍，战力定位为中 Boss。",
        "参数基于 FGO 通行资料做 Labyrinth 异常召唤调整；具体战斗表现需查源。"
      ]
    },
    {
      "id": "arthur-pendragon-saber-prototype",
      "name": "亚瑟·潘德拉贡",
      "aliases": ["Saber (Prototype)", "Arthur Pendragon", "アーサー・ペンドラゴン", "男性亚瑟王"],
      "className": "Saber",
      "trueName": "亚瑟·潘德拉贡",
      "parameters": {
        "strength": "A",
        "endurance": "B",
        "agility": "B",
        "mana": "A",
        "luck": "A+",
        "noblePhantasm": "A++"
      },
      "noblePhantasms": [
        {
          "name": "约束胜利之剑（Excalibur）",
          "rank": "A++",
          "kind": "对城宝具",
          "summary": "与阿尔托莉雅同质的圣剑，但施加了双重封印；完全解放需满足两个条件。"
        }
      ],
      "notes": [
        "Prototype 世界线的 Saber，男性版亚瑟王。サーヴァント階位第一位。",
        "第一次战争御主为沙条爱歌，第二次为沙条绫香。",
        "高剑技+冷静判断力；与 FSN 阿尔托莉雅是平行存在但非同一人。",
        "参数来源：FGO / Prototype material 通行资料。"
      ]
    },
    {
      "id": "brynhildr-lancer-prototype",
      "name": "布伦希尔德",
      "aliases": ["Lancer (蒼銀)", "Brynhildr", "ブリュンヒルデ"],
      "className": "Lancer",
      "trueName": "布伦希尔德",
      "parameters": {
        "strength": "B+",
        "endurance": "A",
        "agility": "A",
        "mana": "C",
        "luck": "E",
        "noblePhantasm": "B"
      },
      "noblePhantasms": [
        {
          "name": "死亡之爱（Brynhildr Romantia）",
          "rank": "B",
          "kind": "对人宝具",
          "summary": "以爱之深度决定威力的魔枪；对「所爱之人」的特攻效果极高，条件契合时可触及冥界。"
        }
      ],
      "notes": [
        "蒼銀のフラグメンツ Lancer。サーヴァント階位第四位。口调温和，长枪轻挥。",
        "御主为玲珑馆美沙夜。",
        "爱与悲剧的瓦尔基里；行动受北欧宿命观影响。",
        "参数来源：FGO / 蒼銀 material。"
      ]
    },
    {
      "id": "ozymandias-rider-prototype",
      "name": "奥兹曼迪亚斯",
      "aliases": ["Rider (蒼銀)", "Ozymandias", "オジマンディアス", "太阳王", "拉美西斯二世"],
      "className": "Rider",
      "trueName": "奥兹曼迪亚斯",
      "parameters": {
        "strength": "C",
        "endurance": "C",
        "agility": "B",
        "mana": "A",
        "luck": "A+",
        "noblePhantasm": "EX"
      },
      "noblePhantasms": [
        {
          "name": "光辉的大复合神殿（Ramesseum Tentyris）",
          "rank": "EX",
          "kind": "对城宝具",
          "summary": "展开固有结界——巨大神殿复合体；三骑士联手仍互角。附带军船梅塞克忒特与神兽斯芬克斯召唤。"
        }
      ],
      "notes": [
        "蒼銀のフラグメンツ Rider。サーヴァント階位第五位。自称王中之王。",
        "傲岸不逊但认可有王者气度之人；在美沙夜面前展现了罕见的尊重。",
        "规格外的战力：三骑士联手方能对抗。",
        "御主为仁贺征尔。参数来源：FGO / 蒼銀。"
      ]
    },
    {
      "id": "arash-archer-prototype",
      "name": "阿拉什",
      "aliases": ["Archer (蒼銀)", "Arash", "アーラシュ", "弓兵"],
      "className": "Archer",
      "trueName": "阿拉什",
      "parameters": {
        "strength": "B",
        "endurance": "A",
        "agility": "B+",
        "mana": "E",
        "luck": "D",
        "noblePhantasm": "B++"
      },
      "noblePhantasms": [
        {
          "name": "流星一条（Stella）",
          "rank": "B++",
          "kind": "对国宝具",
          "summary": "以自身生命为代价的极大射程宝具；一矢足以改变战争地形。发动后弓兵消灭。"
        }
      ],
      "notes": [
        "蒼銀のフラグメンツ Archer。波斯传说的大英雄。",
        "御主为伊势三盈莉。",
        "正直、温和、舍身为人的品格；与其他从者关系良好。",
        "Stella 是最终手段——发动 = 从者消灭，不可轻易使用。"
      ]
    },
    {
      "id": "yamato-takeru-saber-sr",
      "name": "ヤマトタケル",
      "aliases": ["Saber (Samurai Remnant)", "Yamato Takeru", "日本武尊"],
      "className": "Saber",
      "trueName": "ヤマトタケル",
      "parameters": {
        "strength": "B+",
        "endurance": "B",
        "agility": "A",
        "mana": "C",
        "luck": "A",
        "noblePhantasm": "A"
      },
      "noblePhantasms": [
        {
          "name": "草薙剑",
          "rank": "A",
          "kind": "对人/对军宝具",
          "summary": "日本神话三神器之一的神剑；具备火焰属性与风操作能力。"
        }
      ],
      "notes": [
        "Samurai Remnant 主角从者。古风装束，波浪剑。",
        "起初看不起伊织（「弱い、剑以外の能はないのか？」），后逐渐认可。",
        "对平和的江户街景充满好奇。",
        "参数为根据游戏表现和 FGO 参考的合理估算。"
      ]
    },
    {
      "id": "musashi-berserker-sr",
      "name": "宫本武藏",
      "aliases": ["Berserker (Samurai Remnant)", "Miyamoto Musashi", "宮本武蔵"],
      "className": "Berserker",
      "trueName": "宫本武藏",
      "parameters": {
        "strength": "B",
        "endurance": "C",
        "agility": "A+",
        "mana": "E",
        "luck": "B",
        "noblePhantasm": "A"
      },
      "noblePhantasms": [
        {
          "name": "天下无双·零之位",
          "rank": "A",
          "kind": "对人宝具",
          "summary": "二天一流奥义的从者化体现；以无拍子斩击跨越对手防御。"
        }
      ],
      "notes": [
        "高尾太夫召唤的 Berserker。与伊织的养父同名但是平行存在（FGO系女性武藏）。",
        "Berserker 职阶但保留一定理性；战斗风格为二天一流。",
        "与伊织在师徒与对手之间摇摆——养父同名的从者，但并非同一人。",
        "参数为合理估算。"
      ]
    },
    {
      "id": "okita-souji-saber-redline",
      "name": "冲田总司",
      "aliases": ["Saber (Redline)", "Okita Souji", "沖田総司", "樱Saber"],
      "className": "Saber",
      "trueName": "冲田总司",
      "parameters": {
        "strength": "C",
        "endurance": "E",
        "agility": "A+",
        "mana": "E",
        "luck": "D",
        "noblePhantasm": "C"
      },
      "noblePhantasms": [
        {
          "name": "誓之羽织（Flag of Sincerity）",
          "rank": "B",
          "kind": "对人宝具",
          "summary": "新选组诚旗所化；强化自身全参数。"
        },
        {
          "name": "无明三段突",
          "rank": "N/A",
          "kind": "对人奥义",
          "summary": "三段刺突同时命中同一点的绝技；无法以技术或速度回避。"
        }
      ],
      "notes": [
        "type Redline Saber。新选组一番队组长。",
        "极高的敏捷但耐久极低（肺病体质）；短期爆发力超强但长期战不利。",
        "御主为赤城奏丈。",
        "参数来源：FGO / KOHA-ACE 通行资料。"
      ]
    },
    {
      "id": "oda-nobunaga-archer-redline",
      "name": "织田信长",
      "aliases": ["Archer (Redline)", "Oda Nobunaga", "織田信長", "魔人Archer"],
      "className": "Archer",
      "trueName": "织田信长",
      "parameters": {
        "strength": "B",
        "endurance": "B",
        "agility": "B",
        "mana": "A",
        "luck": "A-",
        "noblePhantasm": "E~EX"
      },
      "noblePhantasms": [
        {
          "name": "三千世界（Three Thousand Worlds）",
          "rank": "E~EX",
          "kind": "对军宝具",
          "summary": "三千挺火绳铳的三段射击；对神性与神秘越高的对手威力越大。"
        }
      ],
      "notes": [
        "type Redline Archer / 魔人アーチャー。第六天魔王。",
        "对「神秘」有特攻：神性、魔术、信仰越强的对手越脆弱。",
        "御主为浅间要。",
        "参数来源：FGO / KOHA-ACE。"
      ]
    },
    {
      "id": "li-shuwen-lancer-redline",
      "name": "李书文",
      "aliases": ["Lancer (Redline)", "Li Shuwen", "李書文", "一击必杀"],
      "className": "Lancer",
      "trueName": "李书文",
      "parameters": {
        "strength": "B",
        "endurance": "C",
        "agility": "A",
        "mana": "E",
        "luck": "E",
        "noblePhantasm": "N/A"
      },
      "noblePhantasms": [
        {
          "name": "无二打",
          "rank": "N/A",
          "kind": "对人宝具(非宝具)",
          "summary": "八极拳极意——一击必杀。非正式宝具但达到宝具级威力。"
        }
      ],
      "notes": [
        "type Redline Lancer。青年体（EXTRA版为老年体）。",
        "纯粹武术家——与 EXTRA 版同一英灵但召唤时期不同导致外观年龄差异。",
        "参数来源：FGO / Redline / EXTRA。"
      ]
    },
    {
      "id": "okada-izo-assassin-redline",
      "name": "冈田以藏",
      "aliases": ["Assassin (Redline)", "Okada Izo", "岡田以蔵", "人斩以藏"],
      "className": "Assassin",
      "trueName": "冈田以藏",
      "parameters": {
        "strength": "C",
        "endurance": "D",
        "agility": "B",
        "mana": "E",
        "luck": "D",
        "noblePhantasm": "C"
      },
      "noblePhantasms": [
        {
          "name": "开辟随所（Settle it in the Mountains）",
          "rank": "C",
          "kind": "对人宝具",
          "summary": "习合所见剑技的瞬间再现——可复制目睹过的任何剑术流派一招。"
        }
      ],
      "notes": [
        "type Redline Assassin。幕末四大人斩之一。",
        "技术天才但教养不足；剑技模仿能力出色但有心理脆弱面。",
        "参数来源：FGO。"
      ]
    },
    {
      "id": "mori-nagayoshi-berserker-redline",
      "name": "森长可",
      "aliases": ["Berserker (Redline)", "Mori Nagayoshi", "森長可", "鬼武蔵"],
      "className": "Berserker",
      "trueName": "森长可",
      "parameters": {
        "strength": "A",
        "endurance": "B",
        "agility": "C",
        "mana": "D",
        "luck": "C",
        "noblePhantasm": "C+"
      },
      "noblePhantasms": [
        {
          "name": "人间无骨（Ningen Mukotsu）",
          "rank": "C+",
          "kind": "对人宝具",
          "summary": "魔枪人间无骨——以暴力碾压为本质的突贯攻击。"
        }
      ],
      "notes": [
        "type Redline Berserker。织田家臣·鬼武蔵。",
        "御主为真经津征尔少佐，通过 IV型英灵拘束具控制。",
        "典型的暴走型 Berserker 但保留战斗本能。",
        "参数来源：FGO。"
      ]
    }
  ]
}
